jupyterlab_pytutor/__init__.py
jupyterlab_pytutor/_version.py
jupyterlab_pytutor-0.2.0.data/data/share/jupyter/labextensions/jupyterlab-pytutor/package.json
jupyterlab_pytutor-0.2.0.data/data/share/jupyter/labextensions/jupyterlab-pytutor/schemas/jupyterlab-pytutor/package.json.orig
jupyterlab_pytutor-0.2.0.data/data/share/jupyter/labextensions/jupyterlab-pytutor/schemas/jupyterlab-pytutor/plugin.json
jupyterlab_pytutor-0.2.0.data/data/share/jupyter/labextensions/jupyterlab-pytutor/static/741.3e3f38c47f1192c375fc.js
jupyterlab_pytutor-0.2.0.data/data/share/jupyter/labextensions/jupyterlab-pytutor/static/747.489546fc8202f2fbc76e.js
jupyterlab_pytutor-0.2.0.data/data/share/jupyter/labextensions/jupyterlab-pytutor/static/remoteEntry.687892375ea90d38f449.js
jupyterlab_pytutor-0.2.0.data/data/share/jupyter/labextensions/jupyterlab-pytutor/static/style.js
jupyterlab_pytutor-0.2.0.data/data/share/jupyter/labextensions/jupyterlab-pytutor/static/third-party-licenses.json
jupyterlab_pytutor-0.2.0.data/data/share/jupyter/labextensions/jupyterlab-pytutor/install.json
jupyterlab_pytutor-0.2.0.dist-info/METADATA
jupyterlab_pytutor-0.2.0.dist-info/WHEEL
jupyterlab_pytutor-0.2.0.dist-info/licenses/LICENSE
jupyterlab_pytutor-0.2.0.dist-info/RECORD
