Metadata-Version: 2.1
Name: jupyterlab-pytutor
Version: 0.2.0
Summary: A JupyterLab extension for pythontutor.com
Project-URL: Homepage, https://github.com/jupyterlab-contrib/jupyterlab-pytutor
Project-URL: Bug Tracker, https://github.com/jupyterlab-contrib/jupyterlab-pytutor/issues
Project-URL: Repository, https://github.com/jupyterlab-contrib/jupyterlab-pytutor.git
Author: JupyterLab Contrib Team
License: BSD 3-Clause License
License-File: LICENSE
Classifier: Framework :: Jupyter
Classifier: Framework :: Jupyter :: JupyterLab
Classifier: Framework :: Jupyter :: JupyterLab :: 4
Classifier: Framework :: Jupyter :: JupyterLab :: Extensions
Classifier: Framework :: Jupyter :: JupyterLab :: Extensions :: Prebuilt
Classifier: License :: OSI Approved :: BSD License
Classifier: Programming Language :: Python
Classifier: Programming Language :: Python :: 3
Classifier: Programming Language :: Python :: 3.8
Classifier: Programming Language :: Python :: 3.9
Classifier: Programming Language :: Python :: 3.10
Classifier: Programming Language :: Python :: 3.11
Requires-Python: >=3.8
